exam_data_helper/__init__.py
exam_data_helper/aws_setup.py
exam_data_helper/dynamo_helper.py
exam_data_helper/load_helper.py
exam_data_helper/main.py
exam_data_helper/s3_helper.py
exam_data_helper/test.py
exam_data_helper/transform_data.py
exam_data_helper-0.1.3.dist-info/METADATA
exam_data_helper-0.1.3.dist-info/WHEEL
exam_data_helper-0.1.3.dist-info/RECORD
